Metadata-Version: 2.1
Name: speakWin
Version: 0.0.2
Summary: Text to Speech Windows Based.
Author-email: ranjitmaity95@gmail.com
